podpac/__init__.py
podpac/algorithm.py
podpac/authentication.py
podpac/compositor.py
podpac/conftest.py
podpac/coordinates.py
podpac/data.py
podpac/interpolators.py
podpac/managers.py
podpac/style.py
podpac/utils.py
podpac/version.py
podpac/alglib/__init__.py
podpac/alglib/climatology.py
podpac/core/__init__.py
podpac/core/authentication.py
podpac/core/common_test_utils.py
podpac/core/node.py
podpac/core/settings.py
podpac/core/style.py
podpac/core/units.py
podpac/core/utils.py
podpac/core/algorithm/__init__.py
podpac/core/algorithm/algorithm.py
podpac/core/algorithm/coord_select.py
podpac/core/algorithm/generic.py
podpac/core/algorithm/reprojection.py
podpac/core/algorithm/signal.py
podpac/core/algorithm/stats.py
podpac/core/algorithm/utility.py
podpac/core/cache/__init__.py
podpac/core/cache/cache_ctrl.py
podpac/core/cache/cache_store.py
podpac/core/cache/disk_cache_store.py
podpac/core/cache/file_cache_store.py
podpac/core/cache/ram_cache_store.py
podpac/core/cache/s3_cache_store.py
podpac/core/cache/utils.py
podpac/core/compositor/__init__.py
podpac/core/compositor/compositor.py
podpac/core/compositor/ordered_compositor.py
podpac/core/compositor/tile_compositor.py
podpac/core/coordinates/__init__.py
podpac/core/coordinates/affine_coordinates.py
podpac/core/coordinates/array_coordinates1d.py
podpac/core/coordinates/base_coordinates.py
podpac/core/coordinates/cfunctions.py
podpac/core/coordinates/coordinates.py
podpac/core/coordinates/coordinates1d.py
podpac/core/coordinates/group_coordinates.py
podpac/core/coordinates/polar_coordinates.py
podpac/core/coordinates/stacked_coordinates.py
podpac/core/coordinates/uniform_coordinates1d.py
podpac/core/coordinates/utils.py
podpac/core/data/__init__.py
podpac/core/data/array_source.py
podpac/core/data/csv_source.py
podpac/core/data/dataset_source.py
podpac/core/data/datasource.py
podpac/core/data/file_source.py
podpac/core/data/h5py_source.py
podpac/core/data/ogc.py
podpac/core/data/ogr.py
podpac-3.5.4.dist-info/LICENSE
podpac-3.5.4.dist-info/METADATA
podpac-3.5.4.dist-info/WHEEL
podpac-3.5.4.dist-info/top_level.txt
podpac-3.5.4.dist-info/RECORD
