Metadata-Version: 2.1
Name: podpac
Version: 3.5.4
Summary: Pipeline for Observational Data Processing, Analysis, and Collaboration
Home-page: https://podpac.org
Author: Creare
License: APACHE 2.0
Classifier: Development Status :: 4 - Beta
Classifier: Intended Audience :: Developers
Classifier: Topic :: Scientific/Engineering :: GIS
Classifier: License :: OSI Approved :: Apache Software License
Classifier: Programming Language :: Python
License-File: LICENSE
Requires-Dist: matplotlib>=2.1
Requires-Dist: numpy>=1.14
Requires-Dist: pint>=0.8
Requires-Dist: scipy>=1.0
Requires-Dist: traitlets>=4.3
Requires-Dist: xarray>=0.10
Requires-Dist: requests>=2.18
Requires-Dist: lazy-import>=0.2.2
Requires-Dist: psutil
Requires-Dist: affine
Requires-Dist: geopy
Requires-Dist: pyproj>=2.4
Provides-Extra: algorithms
Requires-Dist: numexpr>=2.6; extra == "algorithms"
Provides-Extra: all
Requires-Dist: beautifulsoup4>=4.6; extra == "all"
Requires-Dist: h5py>=2.9; extra == "all"
Requires-Dist: lxml>=4.2; extra == "all"
Requires-Dist: pydap>=3.3; extra == "all"
Requires-Dist: rasterio>=1.0; extra == "all"
Requires-Dist: zarr>=2.3; extra == "all"
Requires-Dist: owslib; extra == "all"
Requires-Dist: h5netcdf; extra == "all"
Requires-Dist: awscli>=1.16; extra == "all"
Requires-Dist: boto3>=1.9.200; extra == "all"
Requires-Dist: s3fs>=0.4; extra == "all"
Requires-Dist: numexpr>=2.6; extra == "all"
Requires-Dist: jupyterlab; extra == "all"
Requires-Dist: ipyleaflet; extra == "all"
Requires-Dist: ipywidgets; extra == "all"
Requires-Dist: ipympl; extra == "all"
Requires-Dist: nodejs; extra == "all"
Requires-Dist: sat-search>=0.2; extra == "all"
Requires-Dist: sat-stac>=0.3; extra == "all"
Requires-Dist: numpydoc; extra == "all"
Requires-Dist: pylint>=1.8.2; extra == "all"
Requires-Dist: pytest-cov>=2.5.1; extra == "all"
Requires-Dist: pytest-html>=1.7.0; extra == "all"
Requires-Dist: pytest-remotedata>=0.3.1; extra == "all"
Requires-Dist: myst-parser>=1.0.0; extra == "all"
Requires-Dist: coveralls>=1.3; extra == "all"
Requires-Dist: six>=1.0; extra == "all"
Requires-Dist: attrs>=17.4.0; extra == "all"
Requires-Dist: pre-commit>=1; extra == "all"
Requires-Dist: sphinx<3.0,>=2.3; extra == "all"
Requires-Dist: sphinx-rtd-theme>=0.4; extra == "all"
Requires-Dist: sphinx-autobuild>=0.7; extra == "all"
Requires-Dist: pytest>=5.0; extra == "all"
Provides-Extra: aws
Requires-Dist: awscli>=1.16; extra == "aws"
Requires-Dist: boto3>=1.9.200; extra == "aws"
Requires-Dist: s3fs>=0.4; extra == "aws"
Provides-Extra: datatype
Requires-Dist: beautifulsoup4>=4.6; extra == "datatype"
Requires-Dist: h5py>=2.9; extra == "datatype"
Requires-Dist: lxml>=4.2; extra == "datatype"
Requires-Dist: pydap>=3.3; extra == "datatype"
Requires-Dist: rasterio>=1.0; extra == "datatype"
Requires-Dist: zarr>=2.3; extra == "datatype"
Requires-Dist: owslib; extra == "datatype"
Requires-Dist: h5netcdf; extra == "datatype"
Provides-Extra: dev
Requires-Dist: pylint>=1.8.2; extra == "dev"
Requires-Dist: pytest-cov>=2.5.1; extra == "dev"
Requires-Dist: pytest-html>=1.7.0; extra == "dev"
Requires-Dist: pytest-remotedata>=0.3.1; extra == "dev"
Requires-Dist: myst-parser>=1.0.0; extra == "dev"
Requires-Dist: coveralls>=1.3; extra == "dev"
Requires-Dist: six>=1.0; extra == "dev"
Requires-Dist: attrs>=17.4.0; extra == "dev"
Requires-Dist: pre-commit>=1; extra == "dev"
Requires-Dist: sphinx<3.0,>=2.3; extra == "dev"
Requires-Dist: sphinx-rtd-theme>=0.4; extra == "dev"
Requires-Dist: sphinx-autobuild>=0.7; extra == "dev"
Requires-Dist: pytest>=5.0; extra == "dev"
Requires-Dist: numpydoc; extra == "dev"
Provides-Extra: devall
Requires-Dist: beautifulsoup4>=4.6; extra == "devall"
Requires-Dist: h5py>=2.9; extra == "devall"
Requires-Dist: lxml>=4.2; extra == "devall"
Requires-Dist: pydap>=3.3; extra == "devall"
Requires-Dist: rasterio>=1.0; extra == "devall"
Requires-Dist: zarr>=2.3; extra == "devall"
Requires-Dist: owslib; extra == "devall"
Requires-Dist: h5netcdf; extra == "devall"
Requires-Dist: awscli>=1.16; extra == "devall"
Requires-Dist: boto3>=1.9.200; extra == "devall"
Requires-Dist: s3fs>=0.4; extra == "devall"
Requires-Dist: numexpr>=2.6; extra == "devall"
Requires-Dist: jupyterlab; extra == "devall"
Requires-Dist: ipyleaflet; extra == "devall"
Requires-Dist: ipywidgets; extra == "devall"
Requires-Dist: ipympl; extra == "devall"
Requires-Dist: nodejs; extra == "devall"
Requires-Dist: sat-search>=0.2; extra == "devall"
Requires-Dist: sat-stac>=0.3; extra == "devall"
Requires-Dist: numpydoc; extra == "devall"
Requires-Dist: pylint>=1.8.2; extra == "devall"
Requires-Dist: pytest-cov>=2.5.1; extra == "devall"
Requires-Dist: pytest-html>=1.7.0; extra == "devall"
Requires-Dist: pytest-remotedata>=0.3.1; extra == "devall"
Requires-Dist: myst-parser>=1.0.0; extra == "devall"
Requires-Dist: coveralls>=1.3; extra == "devall"
Requires-Dist: six>=1.0; extra == "devall"
Requires-Dist: attrs>=17.4.0; extra == "devall"
Requires-Dist: pre-commit>=1; extra == "devall"
Requires-Dist: sphinx<3.0,>=2.3; extra == "devall"
Requires-Dist: sphinx-rtd-theme>=0.4; extra == "devall"
Requires-Dist: sphinx-autobuild>=0.7; extra == "devall"
Requires-Dist: pytest>=5.0; extra == "devall"
Provides-Extra: node_ui
Requires-Dist: numpydoc; extra == "node-ui"
Provides-Extra: notebook
Requires-Dist: jupyterlab; extra == "notebook"
Requires-Dist: ipyleaflet; extra == "notebook"
Requires-Dist: ipywidgets; extra == "notebook"
Requires-Dist: ipympl; extra == "notebook"
Requires-Dist: nodejs; extra == "notebook"
Provides-Extra: stac
Requires-Dist: sat-search>=0.2; extra == "stac"
Requires-Dist: sat-stac>=0.3; extra == "stac"
